LICENSE
MANIFEST.in
README.rst
setup.py
htmlmin/__init__.py
htmlmin/command.py
htmlmin/decorator.py
htmlmin/escape.py
htmlmin/main.py
htmlmin/middleware.py
htmlmin/parser.py
htmlmin.egg-info/PKG-INFO
htmlmin.egg-info/SOURCES.txt
htmlmin.egg-info/dependency_links.txt
htmlmin.egg-info/entry_points.txt
htmlmin.egg-info/top_level.txt
htmlmin.egg-info/zip-safe
htmlmin/python3html/__init__.py
htmlmin/python3html/parser.py