Metadata-Version: 1.1
Name: htmlmin
Version: 0.1.12
Summary: An HTML Minifier
Home-page: https://htmlmin.readthedocs.io/en/latest/
Author: Dave Mankoff
Author-email: mankyd@gmail.com
License: BSD
Download-URL: https://github.com/mankyd/htmlmin
Platform: UNKNOWN
Classifier: Development Status :: 4 - Beta
Classifier: Intended Audience :: Developers
Classifier: License :: OSI Approved :: BSD License
Classifier: Operating System :: OS Independent
Classifier: Programming Language :: Python
Classifier: Programming Language :: Python :: 2.7
Classifier: Programming Language :: Python :: 3.2
Classifier: Topic :: Text Processing :: Markup :: HTML
